README.md
setup.py
one_quant_data/__init__.py
one_quant_data/data_engine.py
one_quant_data.egg-info/PKG-INFO
one_quant_data.egg-info/SOURCES.txt
one_quant_data.egg-info/dependency_links.txt
one_quant_data.egg-info/requires.txt
one_quant_data.egg-info/top_level.txt