Metadata-Version: 2.1
Name: one-quant-data
Version: 0.1.6
Summary: Data engine for stockA quant
Home-page: https://github.com/onewayforever/one-quant-data
Author: onewayforever
Author-email: onewayforever@163.com
License: UNKNOWN
Platform: UNKNOWN
